mixsimulator/Evaluation.py
mixsimulator/LICENSE
mixsimulator/MANIFEST.in
mixsimulator/Mas_platform.py
mixsimulator/MixSimulator.py
mixsimulator/README.md
mixsimulator/__init__.py
mixsimulator/base.py
mixsimulator/test_classic.py
mixsimulator/test_mas.py
mixsimulator/Experiments/Scenario_type.py
mixsimulator/agents/Agent.py
mixsimulator/agents/Interfaces.py
mixsimulator/agents/Moderator.py
mixsimulator/agents/__init__.py
mixsimulator/data/.DS_Store
mixsimulator/data/dataset_CANVAS_fr.xlsx
mixsimulator/data/dataset_demand_CANVAS_fr.xlsx
mixsimulator/data/dataset_variation_CANVAS_fr.xlsx
mixsimulator/data/RIToamasina/.~lock.dataset_RI_Toamasina_v2.csv#
mixsimulator/data/RIToamasina/DIR-TOAMASINA_concat.csv
mixsimulator/data/RIToamasina/dataset_RI_Toamasina.csv
mixsimulator/data/RIToamasina/dataset_RI_Toamasina_v2.csv
mixsimulator/data/RIToamasina/dataset_RI_Toamasina_variation_template.csv
mixsimulator/data/RIToamasina/demand/.~lock.toamasina_demand.csv#
mixsimulator/data/RIToamasina/demand/toamasina_demand.csv
mixsimulator/demand/__init__.py
mixsimulator/demand/classic/Demand.py
mixsimulator/demand/classic/__init__.py
mixsimulator/demand/mas/Demand.py
mixsimulator/demand/mas/__init__.py
mixsimulator/nevergradBased/Optimizer.py
mixsimulator/nevergradBased/__init__.py
mixsimulator/params_files/exchange_code.json
mixsimulator/params_files/settings.json
mixsimulator/power_plants/__init__.py
mixsimulator/power_plants/classic/HydroCentral.py
mixsimulator/power_plants/classic/PowerCentral.py
mixsimulator/power_plants/classic/__init__.py
mixsimulator/power_plants/mas/Hydropowerplant.py
mixsimulator/power_plants/mas/PowerPlant.py
mixsimulator/power_plants/mas/Thermalpowerplant.py
mixsimulator/power_plants/mas/__init__.py
mixsimulator-0.4.6.dist-info/LICENSE
mixsimulator-0.4.6.dist-info/METADATA
mixsimulator-0.4.6.dist-info/WHEEL
mixsimulator-0.4.6.dist-info/top_level.txt
mixsimulator-0.4.6.dist-info/RECORD
