Metadata-Version: 2.1
Name: mixsimulator
Version: 0.4.6
Summary: Python application with nevergrad optimization model for calculating and simulating the least cost of an energy Mix under constraints.
Home-page: https://github.com/Foloso/MixSimulator
Author: RASOANAIVO Andry, ANDRIAMALALA Rahamefy Solofohanitra, ANDRIAMIZAKASON Toky Axel
Author-email: tokyandriaxel@gmail.com
License: UNKNOWN
Platform: UNKNOWN
Classifier: Programming Language :: Python :: 3
Classifier: License :: OSI Approved :: MIT License
Classifier: Operating System :: OS Independent
Requires-Python: >=3.6
